{"categories":["region","universe"],"contents":[{"categories":["region"],"container":9,"contents":[{"categories":["landscape"],"container":10,"contents":[],"description":false,"facing":1,"gravity":0,"id":11,"label":false,"linearDampening":0.9,"sprite":{"name":"blockStoneTall","tileX":true,"tileY":false,"scrollSpeed":1},"type":"Idea","x":0,"y":3933,"z":5},{"categories":["activatable","door"],"container":10,"contents":[],"description":false,"facing":1,"gravity":0,"id":12,"label":false,"linearDampening":0.9,"sprite":{"name":"door01","tileX":false,"tileY":false,"scrollSpeed":1},"type":"Door","x":200,"y":3673.5,"z":100,"targetDoor":15},{"categories":["solid","platform"],"container":10,"contents":[],"description":false,"facing":1,"gravity":0,"id":33,"label":false,"linearDampening":0.9,"sprite":{"name":"blockStoneTall","tileX":false,"tileY":false,"scrollSpeed":1},"type":"Platform","x":860.150000000001,"y":3352,"z":100},{"categories":["alive","entity","physical","undead"],"container":10,"contents":[],"description":false,"facing":1,"gravity":3.8,"id":36,"label":false,"linearDampening":0.9,"sprite":{"name":"skeleton","tileX":false,"tileY":false,"scrollSpeed":1},"type":"Skeleton","x":1777.1500000000208,"y":3803.5,"z":200,"baseGoal":6,"stats":{"accel":1.5,"health":100,"perception":800,"jump":85,"speed":11.443302038125694,"strength":10,"focus":{"x":2432.3753057979047,"y":3803.5}}}],"description":false,"facing":1,"gravity":0,"id":10,"label":false,"linearDampening":0.9,"sprite":false,"type":"Region","x":10,"y":10,"z":0,"buffer":{"left":0,"top":0,"right":0,"bottom":166}},{"categories":["region"],"container":9,"contents":[{"categories":["landscape"],"container":13,"contents":[],"description":false,"facing":1,"gravity":0,"id":14,"label":false,"linearDampening":0.9,"sprite":{"name":"blockGrass","tileX":true,"tileY":false,"scrollSpeed":1},"type":"Idea","x":0,"y":3965,"z":5},{"categories":["activatable","door"],"container":13,"contents":[],"description":false,"facing":1,"gravity":0,"id":15,"label":false,"linearDampening":0.9,"sprite":{"name":"door01","tileX":false,"tileY":false,"scrollSpeed":1},"type":"Door","x":1401,"y":3691,"z":100,"targetDoor":12},{"categories":["solid","platform"],"container":13,"contents":[],"description":false,"facing":1,"gravity":0,"id":16,"label":false,"linearDampening":0.9,"sprite":{"name":"blockStoneTall","tileX":false,"tileY":false,"scrollSpeed":1},"type":"Platform","x":690,"y":3340,"z":100},{"categories":["alive","entity","physical","undead"],"container":13,"contents":[],"description":false,"facing":1,"gravity":3.8,"id":17,"label":false,"linearDampening":0.9,"sprite":{"name":"skeleton","tileX":false,"tileY":false,"scrollSpeed":1},"type":"Skeleton","x":5840.909392909942,"y":3867.5,"z":200,"baseGoal":6,"stats":{"accel":1.5,"health":100,"perception":800,"jump":85,"speed":8.236762572079897,"strength":10,"focus":{"x":8554.126888047904,"y":3867.5}}},{"categories":["alive","entity","physical","undead"],"container":13,"contents":[],"description":false,"facing":-1,"gravity":3.8,"id":18,"label":false,"linearDampening":0.9,"sprite":{"name":"skeleton","tileX":false,"tileY":false,"scrollSpeed":1},"type":"Skeleton","x":1003.1657309636242,"y":3867.5,"z":200,"baseGoal":6,"stats":{"accel":1.5,"health":100,"perception":800,"jump":85,"speed":16.66227692179382,"strength":10,"focus":{"x":102.38657938316464,"y":3867.5}}},{"categories":["alive","entity","physical","undead"],"container":13,"contents":[],"description":false,"facing":1,"gravity":3.8,"id":19,"label":false,"linearDampening":0.9,"sprite":{"name":"skeleton","tileX":false,"tileY":false,"scrollSpeed":1},"type":"Skeleton","x":679.5063514164552,"y":3867.5,"z":200,"baseGoal":6,"stats":{"accel":1.5,"health":100,"perception":800,"jump":85,"speed":14.85670957621187,"strength":10,"focus":{"x":2605.2469573915005,"y":3867.5}}},{"categories":["alive","entity","physical","undead"],"container":13,"contents":[],"description":false,"facing":1,"gravity":3.8,"id":20,"label":false,"linearDampening":0.9,"sprite":{"name":"skeleton","tileX":false,"tileY":false,"scrollSpeed":1},"type":"Skeleton","x":6587.099999999672,"y":3867.5,"z":200,"baseGoal":6,"stats":{"accel":1.5,"health":100,"perception":800,"jump":85,"speed":4.680714206304402,"strength":10,"focus":{"x":8237.585159949958,"y":3867.5}}},{"categories":["alive","entity","physical","undead"],"container":13,"contents":[],"description":false,"facing":-1,"gravity":3.8,"id":21,"label":false,"linearDampening":0.9,"sprite":{"name":"skeleton","tileX":false,"tileY":false,"scrollSpeed":1},"type":"Skeleton","x":5687.706742625402,"y":3867.5,"z":200,"baseGoal":6,"stats":{"accel":1.5,"health":100,"perception":800,"jump":85,"speed":3.544728694483638,"strength":10,"focus":{"x":1377.0949258469045,"y":3867.5}}},{"categories":["alive","entity","physical","undead"],"container":13,"contents":[],"description":false,"facing":-1,"gravity":3.8,"id":22,"label":false,"linearDampening":0.9,"sprite":{"name":"skeleton","tileX":false,"tileY":false,"scrollSpeed":1},"type":"Skeleton","x":4434.546879531177,"y":3867.5,"z":200,"baseGoal":6,"stats":{"accel":1.5,"health":100,"perception":800,"jump":85,"speed":4.352459313347936,"strength":10,"focus":{"x":1847.0244971103966,"y":3867.5}}},{"categories":["alive","entity","physical","undead"],"container":13,"contents":[],"description":false,"facing":-1,"gravity":3.8,"id":23,"label":false,"linearDampening":0.9,"sprite":{"name":"skeleton","tileX":false,"tileY":false,"scrollSpeed":1},"type":"Skeleton","x":3704.7490012321055,"y":3867.5,"z":200,"baseGoal":6,"stats":{"accel":1.5,"health":100,"perception":800,"jump":85,"speed":15.704605963081123,"strength":10,"focus":{"x":2471.8394316732883,"y":3867.5}}},{"categories":["alive","entity","physical","undead"],"container":13,"contents":[],"description":false,"facing":1,"gravity":3.8,"id":24,"label":false,"linearDampening":0.9,"sprite":{"name":"skeleton","tileX":false,"tileY":false,"scrollSpeed":1},"type":"Skeleton","x":4847.509149790731,"y":3867.5,"z":200,"baseGoal":6,"stats":{"accel":1.5,"health":100,"perception":800,"jump":85,"speed":17.474802067037675,"strength":10,"focus":{"x":9615.099292714149,"y":3867.5}}},{"categories":["alive","entity","physical","undead"],"container":13,"contents":[],"description":false,"facing":-1,"gravity":3.8,"id":25,"label":false,"linearDampening":0.9,"sprite":{"name":"skeleton","tileX":false,"tileY":false,"scrollSpeed":1},"type":"Skeleton","x":6598.800000000009,"y":3867.5,"z":200,"baseGoal":6,"stats":{"accel":1.5,"health":100,"perception":800,"jump":85,"speed":10.816132873762399,"strength":10,"focus":{"x":4661.598089151084,"y":3867.5}}},{"categories":["alive","entity","physical","undead"],"container":13,"contents":[],"description":false,"facing":1,"gravity":3.8,"id":26,"label":false,"linearDampening":0.9,"sprite":{"name":"skeleton","tileX":false,"tileY":false,"scrollSpeed":1},"type":"Skeleton","x":3567.188806458359,"y":3867.5,"z":200,"baseGoal":6,"stats":{"accel":1.5,"health":100,"perception":800,"jump":85,"speed":14.61741573177278,"strength":10,"focus":{"x":8981.725370977074,"y":3867.5}}},{"categories":["alive","entity","physical","undead"],"container":13,"contents":[],"description":false,"facing":-1,"gravity":3.8,"id":27,"label":false,"linearDampening":0.9,"sprite":{"name":"skeleton","tileX":false,"tileY":false,"scrollSpeed":1},"type":"Skeleton","x":9126.78855794843,"y":3867.5,"z":200,"baseGoal":6,"stats":{"accel":1.5,"health":100,"perception":800,"jump":85,"speed":5.159332493320108,"strength":10,"focus":{"x":8125.145144294947,"y":3867.5}}},{"categories":["alive","entity","physical","undead"],"container":13,"contents":[],"description":false,"facing":-1,"gravity":3.8,"id":28,"label":false,"linearDampening":0.9,"sprite":{"name":"skeleton","tileX":false,"tileY":false,"scrollSpeed":1},"type":"Skeleton","x":4565.999999999939,"y":3867.5,"z":200,"baseGoal":6,"stats":{"accel":1.5,"health":100,"perception":800,"jump":85,"speed":7.632964791264385,"strength":10,"focus":{"x":2875.3948397934437,"y":3867.5}}},{"categories":["alive","entity","physical","undead"],"container":13,"contents":[],"description":false,"facing":1,"gravity":3.8,"id":29,"label":false,"linearDampening":0.9,"sprite":{"name":"skeleton","tileX":false,"tileY":false,"scrollSpeed":1},"type":"Skeleton","x":6535.14352599461,"y":3867.5,"z":200,"baseGoal":6,"stats":{"accel":1.5,"health":100,"perception":800,"jump":85,"speed":12.043030419852586,"strength":10,"focus":{"x":8739.809223916382,"y":3867.5}}},{"categories":["alive","entity","physical","undead"],"container":13,"contents":[],"description":false,"facing":-1,"gravity":3.8,"id":30,"label":false,"linearDampening":0.9,"sprite":{"name":"skeleton","tileX":false,"tileY":false,"scrollSpeed":1},"type":"Skeleton","x":7468.612101422938,"y":3867.5,"z":200,"baseGoal":6,"stats":{"accel":1.5,"health":100,"perception":800,"jump":85,"speed":8.199264904949814,"strength":10,"focus":{"x":1984.5739169977605,"y":3867.5}}},{"categories":["entity","undead","physical","alive"],"container":13,"contents":[],"description":false,"facing":1,"gravity":3.8,"id":31,"label":false,"linearDampening":0.9,"sprite":{"name":"skeleton","tileX":false,"tileY":false,"scrollSpeed":1},"type":"Skeleton","x":6107.1000000000195,"y":3867.5,"z":200,"baseGoal":6,"stats":{"accel":1.5,"health":100,"perception":800,"jump":85,"speed":7.8318821783177555,"strength":10,"focus":{"x":7620.3348999843,"y":3867.5},"timeOfDeath":1418368253596}},{"categories":["solid","platform"],"container":13,"contents":[],"description":false,"facing":1,"gravity":0,"id":34,"label":false,"linearDampening":0.9,"sprite":{"name":"blockStoneTall","tileX":false,"tileY":false,"scrollSpeed":1},"type":"Platform","x":405,"y":3340,"z":100},{"categories":["solid","platform"],"container":13,"contents":[],"description":false,"facing":1,"gravity":0,"id":35,"label":false,"linearDampening":0.9,"sprite":{"name":"blockStoneTall","tileX":false,"tileY":false,"scrollSpeed":1},"type":"Platform","x":918,"y":3370,"z":100}],"description":false,"facing":1,"gravity":0,"id":13,"label":false,"linearDampening":0.9,"sprite":false,"type":"SkeletonForest","x":20,"y":10,"z":0,"buffer":{"left":0,"top":0,"right":0,"bottom":102}}],"description":false,"facing":1,"gravity":0,"id":9,"label":false,"linearDampening":0.9,"sprite":false,"type":"Universe","x":0,"y":0,"z":0,"buffer":{"left":0,"top":0,"right":0,"bottom":0}}